piquant/__init__.py
piquant/_bootstrap.py
piquant/libpiquant.so
piquant/torch.py
pypiquant.libs/libgcc_s-2298274a.so.1
pypiquant.libs/libstdc++-08d5c7eb.so.6.0.33
pypiquant-4.1.0.dist-info/METADATA
pypiquant-4.1.0.dist-info/WHEEL
pypiquant-4.1.0.dist-info/top_level.txt
pypiquant-4.1.0.dist-info/RECORD
