Metadata-Version: 2.1
Name: pypiquant
Version: 4.1.0
Summary: Multithreaded SIMD int8 and int4 quantization kernels.
Home-page: https://github.com/PrimeIntellect-ai/pi-quant
Author: Mario Sieg
Author-email: Mario Sieg <mario.sieg.64@gmail.com>
Project-URL: Documentation, https://github.com/PrimeIntellect-ai/pi-quant
Project-URL: Repository, https://github.com/PrimeIntellect-ai/pi-quant
Project-URL: Issues, https://github.com/PrimeIntellect-ai/pi-quant/issues
Requires-Dist: cffi
Requires-Dist: torch
Requires-Dist: numpy
Provides-Extra: dev
Requires-Dist: pytest; extra == "dev"
Requires-Dist: torch; extra == "dev"
Requires-Dist: numpy; extra == "dev"
Requires-Dist: pre-commit; extra == "dev"
Requires-Dist: ruff; extra == "dev"
Requires-Dist: matplotlib; extra == "dev"
Requires-Dist: twine; extra == "dev"
